setup.py
d3/__init__.py
d3/models.py
d3/static/js/d3.js
d3/static/js/d3.min.js
django_d3.egg-info/PKG-INFO
django_d3.egg-info/SOURCES.txt
django_d3.egg-info/dependency_links.txt
django_d3.egg-info/top_level.txt