Metadata-Version: 1.1
Name: django-d3
Version: 3.3.11
Summary: Django package for d3
Home-page: https://github.com/mikebryant/django-d3
Author: Mike Bryant
Author-email: mike@mikebryant.me.uk
License: BSD license
Keywords: django,d3,staticfiles
Platform: any
Classifier: Development Status :: 5 - Production/Stable
Classifier: Environment :: Web Environment
Classifier: Framework :: Django
Classifier: Intended Audience :: Developers
Classifier: Natural Language :: English
Classifier: Operating System :: OS Independent
Classifier: Programming Language :: Python
Classifier: Topic :: Utilities
